{
  "id" : "p2",
  "metainfo" : {
    "label" : "p2",
    "autoLayout" : false,
    "version" : 1,
    "configuration" : {
      "schema" : {
        "type" : "record",
        "fields" : [ ]
      }
    }
  },
  "processes" : {
    "4yHITiE4wNKNwf3gYX6pM$$6u5EBcS0-6fPJUobYLiP7" : {
      "id" : "4yHITiE4wNKNwf3gYX6pM$$6u5EBcS0-6fPJUobYLiP7",
      "component" : "OrchestrationTarget",
      "kind" : "SFTPTarget",
      "metadata" : {
        "label" : "book_inventory_csv_1",
        "x" : -1080,
        "y" : -860,
        "phase" : 0
      },
      "properties" : {
        "connector" : {
          "kind" : "sftp",
          "properties" : {
            "id" : "sftp"
          },
          "type" : "connector"
        },
        "format" : {
          "category" : "file",
          "kind" : "xlsx",
          "properties" : {
            "header" : true,
            "ignoreCellFormatting" : true,
            "sheetName" : "Sheet1"
          }
        },
        "properties" : {
          "filePath" : {
            "type" : "concat_operation",
            "properties" : {
              "elements" : [ {
                "type" : "literal",
                "properties" : {
                  "value" : "/prophecy-sftp/aruns/resutlst_outoput.xlsx"
                }
              } ]
            }
          }
        }
      },
      "ports" : {
        "inputs" : [ {
          "id" : "ph4a5DQT2fwPN0uccM9gO$$tJ6kfYWGftuRY7p1lv7wi",
          "schema" : {
            "entityType" : "",
            "providerType" : "databricks",
            "fields" : [ {
              "name" : "@id",
              "dataType" : {
                "type" : "String"
              }
            }, {
              "name" : "author",
              "dataType" : {
                "type" : "String"
              }
            }, {
              "name" : "title",
              "dataType" : {
                "type" : "String"
              }
            }, {
              "name" : "genre",
              "dataType" : {
                "type" : "String"
              }
            }, {
              "name" : "price",
              "dataType" : {
                "type" : "Double"
              }
            }, {
              "name" : "publish_date",
              "dataType" : {
                "type" : "Date"
              }
            }, {
              "name" : "data_type",
              "dataType" : {
                "type" : "String"
              }
            }, {
              "name" : "data_value",
              "dataType" : {
                "type" : "Struct",
                "fields" : [ {
                  "name" : "id",
                  "dataType" : {
                    "type" : "Bigint"
                  },
                  "description" : "Unique identifier for the data entry"
                }, {
                  "name" : "category",
                  "dataType" : {
                    "type" : "String"
                  },
                  "description" : "Category of the data item"
                }, {
                  "name" : "item",
                  "dataType" : {
                    "type" : "Array",
                    "dataType" : {
                      "type" : "String"
                    }
                  },
                  "description" : "List of items associated with the data value"
                } ]
              }
            }, {
              "name" : "description",
              "dataType" : {
                "type" : "String"
              }
            } ]
          },
          "slug" : "in"
        } ],
        "outputs" : [ ],
        "isCustomOutputSchema" : false
      }
    },
    "_Mj4yjA1aBoVoLhn6zd-e$$uiKjdYjpEoqeGlbPbusS9" : {
      "id" : "_Mj4yjA1aBoVoLhn6zd-e$$uiKjdYjpEoqeGlbPbusS9",
      "component" : "OrchestrationTarget",
      "kind" : "SFTPTarget",
      "metadata" : {
        "label" : "book_inventory_csv_2",
        "x" : -740,
        "y" : -760,
        "phase" : 0
      },
      "properties" : {
        "connector" : {
          "kind" : "sftp",
          "type" : "connector",
          "properties" : {
            "id" : "sftp"
          }
        },
        "properties" : {
          "filePath" : {
            "type" : "concat_operation",
            "properties" : {
              "elements" : [ {
                "type" : "literal",
                "properties" : {
                  "value" : "/prophecy-sftp/aruns/resutlst_outoput.csv"
                }
              } ]
            }
          }
        },
        "format" : {
          "properties" : {
            "separator" : ",",
            "header" : true
          },
          "kind" : "csv",
          "category" : "file"
        }
      },
      "ports" : {
        "inputs" : [ {
          "id" : "8-m_WZcd5Ptr3gELmYgQf$$GEqZ5PPE8TO52UIPCab53",
          "schema" : {
            "entityType" : "",
            "providerType" : "databricks",
            "fields" : [ {
              "name" : "@id",
              "dataType" : {
                "type" : "String"
              }
            }, {
              "name" : "author",
              "dataType" : {
                "type" : "String"
              }
            }, {
              "name" : "title",
              "dataType" : {
                "type" : "String"
              }
            }, {
              "name" : "genre",
              "dataType" : {
                "type" : "String"
              }
            }, {
              "name" : "price",
              "dataType" : {
                "type" : "Double"
              }
            }, {
              "name" : "publish_date",
              "dataType" : {
                "type" : "Date"
              }
            }, {
              "name" : "data_type",
              "dataType" : {
                "type" : "String"
              }
            }, {
              "name" : "data_value",
              "dataType" : {
                "type" : "Struct",
                "fields" : [ {
                  "name" : "id",
                  "dataType" : {
                    "type" : "Bigint"
                  },
                  "description" : "Unique identifier for the data entry"
                }, {
                  "name" : "category",
                  "dataType" : {
                    "type" : "String"
                  },
                  "description" : "Category of the data item"
                }, {
                  "name" : "item",
                  "dataType" : {
                    "type" : "Array",
                    "dataType" : {
                      "type" : "String"
                    }
                  },
                  "description" : "List of items associated with the data value"
                } ]
              }
            }, {
              "name" : "description",
              "dataType" : {
                "type" : "String"
              }
            } ]
          },
          "slug" : "in"
        } ],
        "outputs" : [ ],
        "isCustomOutputSchema" : false
      }
    },
    "YwCwTcYSTuuQ0umBmaUHk$$fayDS7xSKS9BeOX5i9DlZ" : {
      "id" : "YwCwTcYSTuuQ0umBmaUHk$$fayDS7xSKS9BeOX5i9DlZ",
      "component" : "Reformat",
      "metadata" : {
        "label" : "Reformat_1",
        "x" : -1020,
        "y" : -560,
        "phase" : 0
      },
      "properties" : {
        "columnsSelector" : [ "vJ4ebXJitvdcRz-aAgr56$$VWSk3wrvNRAvbh7LBlljw##@id", "vJ4ebXJitvdcRz-aAgr56$$VWSk3wrvNRAvbh7LBlljw##author", "vJ4ebXJitvdcRz-aAgr56$$VWSk3wrvNRAvbh7LBlljw##title", "vJ4ebXJitvdcRz-aAgr56$$VWSk3wrvNRAvbh7LBlljw##genre", "vJ4ebXJitvdcRz-aAgr56$$VWSk3wrvNRAvbh7LBlljw##price", "vJ4ebXJitvdcRz-aAgr56$$VWSk3wrvNRAvbh7LBlljw##publish_date", "vJ4ebXJitvdcRz-aAgr56$$VWSk3wrvNRAvbh7LBlljw##data_type", "vJ4ebXJitvdcRz-aAgr56$$VWSk3wrvNRAvbh7LBlljw##data_value", "vJ4ebXJitvdcRz-aAgr56$$VWSk3wrvNRAvbh7LBlljw##description" ],
        "expressions" : [ {
          "expression" : {
            "expression" : "`@id`"
          },
          "alias" : "`@id`",
          "_row_id" : "709552550"
        }, {
          "expression" : {
            "expression" : "author"
          },
          "alias" : "author",
          "_row_id" : "775422970"
        }, {
          "expression" : {
            "expression" : "title"
          },
          "alias" : "title",
          "_row_id" : "1202150735"
        }, {
          "expression" : {
            "expression" : "genre"
          },
          "alias" : "genre",
          "_row_id" : "2045279162"
        }, {
          "expression" : {
            "expression" : "price"
          },
          "alias" : "price",
          "_row_id" : "190295218"
        }, {
          "expression" : {
            "expression" : "publish_date"
          },
          "alias" : "publish_date",
          "_row_id" : "499567422"
        }, {
          "expression" : {
            "expression" : "data_type"
          },
          "alias" : "data_type",
          "_row_id" : "109791614"
        }, {
          "expression" : {
            "expression" : "data_value"
          },
          "alias" : "data_value",
          "_row_id" : "1253434948"
        }, {
          "expression" : {
            "expression" : "description"
          },
          "alias" : "description",
          "_row_id" : "1506239128"
        } ]
      },
      "ports" : {
        "inputs" : [ {
          "id" : "vJ4ebXJitvdcRz-aAgr56$$VWSk3wrvNRAvbh7LBlljw",
          "slug" : "in0"
        } ],
        "outputs" : [ {
          "id" : "i3syM2K9UsEYiMy3RBIaB$$Q-FbHGm2pm9tz70z9kX5g",
          "slug" : "out"
        } ],
        "isCustomOutputSchema" : false
      }
    },
    "MLS2ztNI3e98DMpvyZMiw" : {
      "id" : "MLS2ztNI3e98DMpvyZMiw",
      "component" : "OrchestrationSource",
      "kind" : "SFTPSource",
      "metadata" : {
        "label" : "SFTPSource_2",
        "x" : -1860,
        "y" : -500,
        "phase" : 0
      },
      "properties" : {
        "connector" : {
          "kind" : "sftp",
          "properties" : {
            "authMethod" : "password",
            "id" : "sftp",
            "port" : 22
          },
          "type" : "connector"
        },
        "format" : {
          "kind" : "xml",
          "properties" : {
            "schema" : {
              "providerType" : "arrow",
              "fields" : [ {
                "name" : "@id",
                "dataType" : {
                  "type" : "String"
                },
                "description" : "Unique identifier for the record"
              }, {
                "name" : "author",
                "dataType" : {
                  "type" : "String"
                },
                "description" : "Name of the author of the book"
              }, {
                "name" : "title",
                "dataType" : {
                  "type" : "String"
                },
                "description" : "The title of the book or publication"
              }, {
                "name" : "genre",
                "dataType" : {
                  "type" : "String"
                },
                "description" : "Category of the book or publication"
              }, {
                "name" : "price",
                "dataType" : {
                  "type" : "Double"
                },
                "description" : "The selling price of the item"
              }, {
                "name" : "publish_date",
                "dataType" : {
                  "type" : "Date"
                },
                "description" : "The date when the item was published"
              }, {
                "name" : "data_type",
                "dataType" : {
                  "type" : "String"
                },
                "description" : "The type of data represented in the record"
              }, {
                "name" : "data_value",
                "dataType" : {
                  "type" : "Struct",
                  "fields" : [ {
                    "name" : "id",
                    "dataType" : {
                      "type" : "Bigint"
                    },
                    "description" : "Unique identifier for the data entry"
                  }, {
                    "name" : "category",
                    "dataType" : {
                      "type" : "String"
                    },
                    "description" : "Category of the data item"
                  }, {
                    "name" : "item",
                    "dataType" : {
                      "type" : "Array",
                      "dataType" : {
                        "type" : "String"
                      }
                    },
                    "description" : "List of items associated with the data value"
                  } ]
                },
                "description" : "Structured data containing detailed information about the item"
              }, {
                "name" : "description",
                "dataType" : {
                  "type" : "String"
                },
                "description" : "A brief overview of the item or content"
              } ]
            }
          }
        },
        "properties" : {
          "filePath" : "/prophecy-sftp/aruns/book_catalog_with_data_types.xml"
        }
      },
      "ports" : {
        "inputs" : [ ],
        "outputs" : [ {
          "id" : "79ef91c2-c791-4a61-9739-f5e7e16ca39b",
          "schema" : {
            "entityType" : "",
            "providerType" : "databricks",
            "fields" : [ {
              "name" : "@id",
              "dataType" : {
                "type" : "String"
              }
            }, {
              "name" : "author",
              "dataType" : {
                "type" : "String"
              }
            }, {
              "name" : "title",
              "dataType" : {
                "type" : "String"
              }
            }, {
              "name" : "genre",
              "dataType" : {
                "type" : "String"
              }
            }, {
              "name" : "price",
              "dataType" : {
                "type" : "Double"
              }
            }, {
              "name" : "publish_date",
              "dataType" : {
                "type" : "Date"
              }
            }, {
              "name" : "data_type",
              "dataType" : {
                "type" : "String"
              }
            }, {
              "name" : "data_value",
              "dataType" : {
                "type" : "Struct",
                "fields" : [ {
                  "name" : "id",
                  "dataType" : {
                    "type" : "Bigint"
                  },
                  "description" : "Unique identifier for the data entry"
                }, {
                  "name" : "category",
                  "dataType" : {
                    "type" : "String"
                  },
                  "description" : "Category of the data item"
                }, {
                  "name" : "item",
                  "dataType" : {
                    "type" : "Array",
                    "dataType" : {
                      "type" : "String"
                    }
                  },
                  "description" : "List of items associated with the data value"
                } ]
              }
            }, {
              "name" : "description",
              "dataType" : {
                "type" : "String"
              }
            } ]
          },
          "slug" : "out0"
        } ]
      }
    },
    "ky5r8V5jFEGQIP2aFplIz$$fwY11mPKgGow7keIwbgEi" : {
      "id" : "ky5r8V5jFEGQIP2aFplIz$$fwY11mPKgGow7keIwbgEi",
      "component" : "OrchestrationTarget",
      "kind" : "SFTPTarget",
      "metadata" : {
        "label" : "book_inventory_csv",
        "x" : -580,
        "y" : -560,
        "phase" : 0
      },
      "properties" : {
        "connector" : {
          "kind" : "sftp",
          "properties" : {
            "id" : "sftp"
          },
          "type" : "connector"
        },
        "format" : {
          "category" : "file",
          "kind" : "xml",
          "properties" : {
            "rootName" : "root",
            "rowTag" : "row"
          }
        },
        "properties" : {
          "filePath" : {
            "type" : "concat_operation",
            "properties" : {
              "elements" : [ {
                "type" : "literal",
                "properties" : {
                  "value" : "/prophecy-sftp/aruns/resutlst_outoput.xml"
                }
              } ]
            }
          }
        }
      },
      "ports" : {
        "inputs" : [ {
          "id" : "-xCtJe3q1yKd3XiZrtTkb$$KYoyyEinBRX_Ju4Cq3k9z",
          "slug" : "in"
        } ],
        "outputs" : [ ],
        "isCustomOutputSchema" : false
      }
    },
    "M_mAPaOGpsay_lGUMKdvm$$_2jU_Xx9pL4GKzzP1oO47" : {
      "id" : "M_mAPaOGpsay_lGUMKdvm$$_2jU_Xx9pL4GKzzP1oO47",
      "component" : "OrchestrationTarget",
      "kind" : "SFTPTarget",
      "metadata" : {
        "label" : "book_inventory_csv_3",
        "x" : -620,
        "y" : -320,
        "phase" : 0
      },
      "properties" : {
        "connector" : {
          "kind" : "sftp",
          "properties" : {
            "id" : "sftp"
          },
          "type" : "connector"
        },
        "format" : {
          "category" : "file",
          "kind" : "json",
          "properties" : { }
        },
        "properties" : {
          "filePath" : {
            "type" : "concat_operation",
            "properties" : {
              "elements" : [ {
                "type" : "literal",
                "properties" : {
                  "value" : "/prophecy-sftp/aruns/resutlst_outoput.json"
                }
              } ]
            }
          }
        }
      },
      "ports" : {
        "inputs" : [ {
          "id" : "p0x0myysUTRaMkOoi1cfc$$8_d4vGiA49WKdXAUUJjcC",
          "schema" : {
            "entityType" : "",
            "providerType" : "databricks",
            "fields" : [ {
              "name" : "@id",
              "dataType" : {
                "type" : "String"
              }
            }, {
              "name" : "author",
              "dataType" : {
                "type" : "String"
              }
            }, {
              "name" : "title",
              "dataType" : {
                "type" : "String"
              }
            }, {
              "name" : "genre",
              "dataType" : {
                "type" : "String"
              }
            }, {
              "name" : "price",
              "dataType" : {
                "type" : "Double"
              }
            }, {
              "name" : "publish_date",
              "dataType" : {
                "type" : "Date"
              }
            }, {
              "name" : "data_type",
              "dataType" : {
                "type" : "String"
              }
            }, {
              "name" : "data_value",
              "dataType" : {
                "type" : "Struct",
                "fields" : [ {
                  "name" : "id",
                  "dataType" : {
                    "type" : "Bigint"
                  },
                  "description" : "Unique identifier for the data entry"
                }, {
                  "name" : "category",
                  "dataType" : {
                    "type" : "String"
                  },
                  "description" : "Category of the data item"
                }, {
                  "name" : "item",
                  "dataType" : {
                    "type" : "Array",
                    "dataType" : {
                      "type" : "String"
                    }
                  },
                  "description" : "List of items associated with the data value"
                } ]
              }
            }, {
              "name" : "description",
              "dataType" : {
                "type" : "String"
              }
            } ]
          },
          "slug" : "in"
        } ],
        "outputs" : [ ],
        "isCustomOutputSchema" : false
      }
    }
  },
  "connections" : [ {
    "id" : "bZOlSUuAvgB5JAKNAHHdi$$Hvm_0loC-9wNsxgX5E8UZ",
    "source" : "MLS2ztNI3e98DMpvyZMiw",
    "sourcePort" : "79ef91c2-c791-4a61-9739-f5e7e16ca39b",
    "target" : "YwCwTcYSTuuQ0umBmaUHk$$fayDS7xSKS9BeOX5i9DlZ",
    "targetPort" : "vJ4ebXJitvdcRz-aAgr56$$VWSk3wrvNRAvbh7LBlljw"
  }, {
    "id" : "i_Dg3RgZxpEHJuN5l2JrG",
    "source" : "YwCwTcYSTuuQ0umBmaUHk$$fayDS7xSKS9BeOX5i9DlZ",
    "sourcePort" : "i3syM2K9UsEYiMy3RBIaB$$Q-FbHGm2pm9tz70z9kX5g",
    "target" : "ky5r8V5jFEGQIP2aFplIz$$fwY11mPKgGow7keIwbgEi",
    "targetPort" : "-xCtJe3q1yKd3XiZrtTkb$$KYoyyEinBRX_Ju4Cq3k9z"
  }, {
    "id" : "XeI_Mgp89vfF3l1lksF7N",
    "source" : "MLS2ztNI3e98DMpvyZMiw",
    "sourcePort" : "79ef91c2-c791-4a61-9739-f5e7e16ca39b",
    "target" : "4yHITiE4wNKNwf3gYX6pM$$6u5EBcS0-6fPJUobYLiP7",
    "targetPort" : "ph4a5DQT2fwPN0uccM9gO$$tJ6kfYWGftuRY7p1lv7wi"
  }, {
    "id" : "WNDBF2FEM7yVzJJlTGO6p",
    "source" : "MLS2ztNI3e98DMpvyZMiw",
    "sourcePort" : "79ef91c2-c791-4a61-9739-f5e7e16ca39b",
    "target" : "_Mj4yjA1aBoVoLhn6zd-e$$uiKjdYjpEoqeGlbPbusS9",
    "targetPort" : "8-m_WZcd5Ptr3gELmYgQf$$GEqZ5PPE8TO52UIPCab53"
  }, {
    "id" : "QiNYdRxyNltkPBS747dI7",
    "source" : "MLS2ztNI3e98DMpvyZMiw",
    "sourcePort" : "79ef91c2-c791-4a61-9739-f5e7e16ca39b",
    "target" : "M_mAPaOGpsay_lGUMKdvm$$_2jU_Xx9pL4GKzzP1oO47",
    "targetPort" : "p0x0myysUTRaMkOoi1cfc$$8_d4vGiA49WKdXAUUJjcC"
  } ],
  "component" : "Pipeline"
}