{
  "id" : "app5",
  "metainfo" : {
    "description" : "",
    "pipelineId" : "pipeline3"
  },
  "definition" : {
    "template" : [ {
      "id" : "DataPreview1",
      "type" : "DataPreview",
      "properties" : {
        "tableId" : "cSyTOZ7vq1Hb6pNG7jHNK$$cOH6tHX7weM_jpLuni8Nk",
        "columns" : [ {
          "key" : "ID",
          "column" : "ID",
          "label" : "ID",
          "selected" : true
        }, {
          "key" : "Name",
          "column" : "Name",
          "label" : "Name",
          "selected" : true
        }, {
          "key" : "Age",
          "column" : "Age",
          "label" : "Age",
          "selected" : true
        }, {
          "key" : "City",
          "column" : "City",
          "label" : "City",
          "selected" : true
        } ],
        "title" : "Table Title"
      },
      "scrollInToView" : false,
      "errors" : { }
    }, {
      "id" : "TextInput1",
      "type" : "TextInput",
      "properties" : {
        "configField" : "string",
        "label" : "Input Label",
        "defaultValue" : "Name"
      },
      "scrollInToView" : false,
      "errors" : { }
    } ]
  },
  "instances" : {
    "config9" : {
      "config" : {
        "string" : "Name"
      },
      "sources" : { },
      "schedule" : {
        "cron" : "* 0 2 * * * *",
        "timeZone" : "GMT",
        "emailOnSuccess" : false,
        "emailOnFailure" : false,
        "emailOnStart" : false,
        "emails" : [ "email@gmail.com" ],
        "enabled" : false
      }
    }
  }
}